{
  "editor.tabSize": 2,
  "editor.fontFamily": "Source Code Pro, Menlo, Monaco, 'Courier New', monospace",
  "editor.minimap.enabled": false,
  "emmet.triggerExpansionOnTab": true,
  "workbench.colorTheme": "Dracula",
  "workbench.iconTheme": "vscode-icons",
  "workbench.startupEditor": "none",
  "php-cs-fixer.onsave": true,
  "php-cs-fixer.config": "$HOME/.vscode/.php_cs",
  "importCost.typescriptExtensions": [
    "\\.vue?$"
  ],
  "eslint.validate": [
    "javascript",
    "javascriptreact",
    "vue",
    "vue-html"
  ],
  "editor.formatOnSave": true,
  "[javascript]": {
    "editor.formatOnSave": false
  },
  "eslint.autoFixOnSave": true,
  "eslint.alwaysShowStatus": true,
  "vetur.validation.template": false
}